yautil/__init__.py
yautil/cacheutil.py
yautil/decorators.py
yautil/dockerutil.py
yautil/eventutil.py
yautil/fcache.py
yautil/fileutil.py
yautil/gitutil.py
yautil/mputil.py
yautil/plotutil.py
yautil/pyshutil.py
yautil/shutil.py
yautil/strutil.py
yautil/subcommand.py
yautil/test.py
yautil/mountutil/__init__.py
yautil/mountutil/api.py
yautil/mountutil/block_dev_handle.py
yautil/mountutil/core.py
yautil/mountutil/types.py
yautil/mountutil/udisksctl.py
yautil/mountutil/mountables/__init__.py
yautil/mountutil/mountables/cpio_archive.py
yautil/mountutil/mountables/disk_image.py
yautil/mountutil/mountables/linux_disk_image.py
yautil/mountutil/mountables/qcow2_image.py
yautil/mountutil/mountables/qemu_qcow2_image.py
yautil/mountutil/mountables/yaffs2_archive.py
yautil/mountutil/yaffs2utils-0.2.9/.gitignore
yautil/mountutil/yaffs2utils-0.2.9/CHANGES
yautil/mountutil/yaffs2utils-0.2.9/COPYING
yautil/mountutil/yaffs2utils-0.2.9/Makefile
yautil/mountutil/yaffs2utils-0.2.9/README
yautil/mountutil/yaffs2utils-0.2.9/configs.h
yautil/mountutil/yaffs2utils-0.2.9/endian_convert.c
yautil/mountutil/yaffs2utils-0.2.9/endian_convert.h
yautil/mountutil/yaffs2utils-0.2.9/list.h
yautil/mountutil/yaffs2utils-0.2.9/mkyaffs2.c
yautil/mountutil/yaffs2utils-0.2.9/mtd-abi.h
yautil/mountutil/yaffs2utils-0.2.9/nand_ecclayout.h
yautil/mountutil/yaffs2utils-0.2.9/progress_bar.c
yautil/mountutil/yaffs2utils-0.2.9/progress_bar.h
yautil/mountutil/yaffs2utils-0.2.9/safe_rw.c
yautil/mountutil/yaffs2utils-0.2.9/safe_rw.h
yautil/mountutil/yaffs2utils-0.2.9/unspare2.c
yautil/mountutil/yaffs2utils-0.2.9/unyaffs2.c
yautil/mountutil/yaffs2utils-0.2.9/version.h
yautil/mountutil/yaffs2utils-0.2.9/yaffs2/yaffs_ecc.c
yautil/mountutil/yaffs2utils-0.2.9/yaffs2/yaffs_ecc.h
yautil/mountutil/yaffs2utils-0.2.9/yaffs2/yaffs_guts.h
yautil/mountutil/yaffs2utils-0.2.9/yaffs2/yaffs_hweight.c
yautil/mountutil/yaffs2utils-0.2.9/yaffs2/yaffs_hweight.h
yautil/mountutil/yaffs2utils-0.2.9/yaffs2/yaffs_packedtags1.c
yautil-0.0.66.dist-info/LICENSE
yautil-0.0.66.dist-info/METADATA
yautil-0.0.66.dist-info/WHEEL
yautil-0.0.66.dist-info/top_level.txt
yautil-0.0.66.dist-info/RECORD
