Metadata-Version: 2.1
Name: yautil
Version: 0.0.66
Summary: Yet Another Python util.
Home-page: https://github.com/dhkim09a/pyutil
Author: Donghwi Kim
Author-email: dhkim09@kaist.ac.kr
Requires-Python: >=3.7
License-File: LICENSE
Requires-Dist: sh
Requires-Dist: matplotlib
Provides-Extra: test
Requires-Dist: sh ; extra == 'test'
Requires-Dist: matplotlib ; extra == 'test'
